driver/__init__.py
daisycc-0.0.1.dist-info/LICENSE
daisycc-0.0.1.dist-info/METADATA
daisycc-0.0.1.dist-info/WHEEL
daisycc-0.0.1.dist-info/entry_points.txt
daisycc-0.0.1.dist-info/top_level.txt
daisycc-0.0.1.dist-info/RECORD
